hnp_codebuddy/__init__.py
hnp_codebuddy/api_client.py
hnp_codebuddy/bitbucket.py
hnp_codebuddy/cli.py
hnp_codebuddy/config.py
hnp_codebuddy-0.1.dist-info/METADATA
hnp_codebuddy-0.1.dist-info/WHEEL
hnp_codebuddy-0.1.dist-info/entry_points.txt
hnp_codebuddy-0.1.dist-info/top_level.txt
hnp_codebuddy-0.1.dist-info/RECORD
