Metadata-Version: 2.2
Name: hnp-codebuddy
Version: 0.1
Requires-Dist: requests
Requires-Dist: python-dotenv
Dynamic: requires-dist
